jobscrape/__init__.py
jobscrape/jobs/__init__.py
jobscrape/scrapers/__init__.py
jobscrape/scrapers/exceptions.py
jobscrape/scrapers/glassdoor/__init__.py
jobscrape/scrapers/indeed/__init__.py
jobscrape/scrapers/linkedin/__init__.py
jobscrape/scrapers/utils.py
jobscrape/scrapers/ziprecruiter/__init__.py
python_jobscrape-1.1.63.dist-info/LICENSE
python_jobscrape-1.1.63.dist-info/METADATA
python_jobscrape-1.1.63.dist-info/WHEEL
python_jobscrape-1.1.63.dist-info/RECORD
