Metadata-Version: 2.1
Name: python-jobscrape
Version: 1.1.63
Summary: Job scraper for LinkedIn, Indeed, Glassdoor & ZipRecruiter
Home-page: https://github.com/nathan102030/jobscrape
Author: Nathan Demssie
Author-email: nsd2145@columbia.edu
Requires-Python: >=3.10,<4.0
Classifier: Programming Language :: Python :: 3
Classifier: Programming Language :: Python :: 3.10
Classifier: Programming Language :: Python :: 3.11
Classifier: Programming Language :: Python :: 3.12
Requires-Dist: NUMPY (==1.24.2)
Requires-Dist: beautifulsoup4 (>=4.12.2,<5.0.0)
Requires-Dist: markdownify (>=0.11.6,<0.12.0)
Requires-Dist: pandas (>=2.1.0,<3.0.0)
Requires-Dist: pydantic (>=2.3.0,<3.0.0)
Requires-Dist: regex (>=2024.4.28,<2025.0.0)
Requires-Dist: requests (>=2.31.0,<3.0.0)
Requires-Dist: tls-client (>=1.0.1,<2.0.0)
